cookieslicer/__init__.py
cookieslicer/__main__.py
cookieslicer/application_base_argument_parser.py
cookieslicer/application_return_code.py
cookieslicer/cookieslicer.py
cookieslicer/cookieslicer_argument_parser.py
cookieslicer/cookieslicer_configuration.py
cookieslicer/cookieslicer_constants.py
cookieslicer/cookieslicer_processor.py
cookieslicer/cookieslicer_template.py
cookieslicer/main.py
cookieslicer/py.typed
cookieslicer/version.py
cookieslicer-0.1.5.dist-info/licenses/LICENSE.txt
cookieslicer-0.1.5.dist-info/METADATA
cookieslicer-0.1.5.dist-info/WHEEL
cookieslicer-0.1.5.dist-info/entry_points.txt
cookieslicer-0.1.5.dist-info/top_level.txt
cookieslicer-0.1.5.dist-info/RECORD
