Metadata-Version: 2.4
Name: cookieslicer
Version: 0.1.5
Summary: Apply advanced templating by smartly using CookieCutter.
Home-page: https://github.com/jackdewinter/cookieslicer
Author: Jack De Winter
Author-email: jack.de.winter@outlook.com
Maintainer: Jack De Winter
Maintainer-email: jack.de.winter@outlook.com
Project-URL: Change Log, https://github.com/jackdewinter/cookieslicer/blob/main/changelog.md
Keywords: cookiecutter
Classifier: Development Status :: 4 - Beta
Classifier: Environment :: Console
Classifier: Intended Audience :: Developers
Classifier: Programming Language :: Python :: 3.9
Classifier: Programming Language :: Python :: 3.10
Classifier: Programming Language :: Python :: 3.11
Classifier: Programming Language :: Python :: 3.12
Classifier: Programming Language :: Python :: 3.13
Classifier: License :: OSI Approved :: MIT License
Classifier: Operating System :: OS Independent
Classifier: Natural Language :: English
Classifier: Topic :: Software Development :: Libraries :: Application Frameworks
Requires-Python: >=3.8.0
License-File: LICENSE.txt
Requires-Dist: typing-extensions>=4.5.0
Requires-Dist: pyyaml>=6.0.1
Requires-Dist: cookiecutter>=2.1.1
Requires-Dist: typed-argument-parser>=1.8.1
Dynamic: author
Dynamic: author-email
Dynamic: classifier
Dynamic: description
Dynamic: description-content-type
Dynamic: home-page
Dynamic: keywords
Dynamic: license-file
Dynamic: maintainer
Dynamic: maintainer-email
Dynamic: project-url
Dynamic: requires-dist
Dynamic: requires-python
Dynamic: summary
